turbohtml/__init__.py
turbohtml/parser.py
turbohtml/validate.py
turbohtml-0.0.0.dist-info/METADATA
turbohtml-0.0.0.dist-info/WHEEL
turbohtml-0.0.0.dist-info/RECORD
