Metadata-Version: 2.4
Name: turbohtml
Version: 0.0.0
Summary: Coming soon
Project-URL: Homepage, https://github.com/emilstenstrom/turbohtml
Project-URL: Issues, https://github.com/emilstenstrom/turbohtml/issues
Author-email: Emil Stenström <emil@emilstenstrom.se>
Classifier: License :: OSI Approved :: MIT License
Classifier: Operating System :: OS Independent
Classifier: Programming Language :: Python :: 3
Requires-Python: >=3.8
